setup.py
cssquery/__init__.py
cssquery/error.py
cssquery/parser.py
cssquery/pseudo.py
cssquery/query.py
cssquery/util.py
cssquery.egg-info/PKG-INFO
cssquery.egg-info/SOURCES.txt
cssquery.egg-info/dependency_links.txt
cssquery.egg-info/requires.txt
cssquery.egg-info/top_level.txt