Metadata-Version: 1.1
Name: cssquery
Version: 0.1.1
Summary: Query objects with CSS selectors
Home-page: https://github.com/bitlang/cssquery
Author: Josh Junon
Author-email: josh@junon.me
License: UNKNOWN
Download-URL: https://github.com/bitlang/cssquery/archive/0.1.1.tar.gz
Keywords: css,select,query,selectors,selector,object,regular,xpath
Platform: UNKNOWN
